ntnx_licensing_py_client/__init__.py
ntnx_licensing_py_client/api_client.py
ntnx_licensing_py_client/api_response.py
ntnx_licensing_py_client/configuration.py
ntnx_licensing_py_client/custom_retry.py
ntnx_licensing_py_client/rest.py
ntnx_licensing_py_client/api/__init__.py
ntnx_licensing_py_client/api/end_user_license_agreement_api.py
ntnx_licensing_py_client/api/license_keys_api.py
ntnx_licensing_py_client/api/licenses_api.py
ntnx_licensing_py_client/models/__init__.py
ntnx_licensing_py_client/models/OneOfcommon/__init__.py
ntnx_licensing_py_client/models/OneOfcommon/v1/__init__.py
ntnx_licensing_py_client/models/OneOfcommon/v1/config/KVPairvalue.py
ntnx_licensing_py_client/models/OneOfcommon/v1/config/__init__.py
ntnx_licensing_py_client/models/OneOflicensing/__init__.py
ntnx_licensing_py_client/models/OneOflicensing/v4/__init__.py
ntnx_licensing_py_client/models/OneOflicensing/v4/agreements/AddUserApiResponsedata.py
ntnx_licensing_py_client/models/OneOflicensing/v4/agreements/GetEulaApiResponsedata.py
ntnx_licensing_py_client/models/OneOflicensing/v4/agreements/__init__.py
ntnx_licensing_py_client/models/OneOflicensing/v4/config/AddLicenseKeyApiResponsedata.py
ntnx_licensing_py_client/models/OneOflicensing/v4/config/AssignLicenseKeysApiResponsedata.py
ntnx_licensing_py_client/models/OneOflicensing/v4/config/AssociateLicenseKeysApiResponsedata.py
ntnx_licensing_py_client/models/OneOflicensing/v4/config/DeleteLicenseKeyApiResponsedata.py
ntnx_licensing_py_client/models/OneOflicensing/v4/config/FeatureProjectionvalue.py
ntnx_licensing_py_client/models/OneOflicensing/v4/config/Featurevalue.py
ntnx_licensing_py_client/models/OneOflicensing/v4/config/GetLicenseKeyApiResponsedata.py
ntnx_licensing_py_client/models/OneOflicensing/v4/config/ListAllowancesApiResponsedata.py
ntnx_licensing_py_client/models/OneOflicensing/v4/config/ListCompliancesApiResponsedata.py
ntnx_licensing_py_client/models/OneOflicensing/v4/config/ListEntitlementsApiResponsedata.py
ntnx_licensing_py_client-4.3.1.dist-info/LICENSE.txt
ntnx_licensing_py_client-4.3.1.dist-info/METADATA
ntnx_licensing_py_client-4.3.1.dist-info/WHEEL
ntnx_licensing_py_client-4.3.1.dist-info/top_level.txt
ntnx_licensing_py_client-4.3.1.dist-info/RECORD
